sigmaepsilon/plotting/mpl/__init__.py
sigmaepsilon/plotting/mpl/d2.py
sigmaepsilon/plotting/mpl/parallel.py
sigmaepsilon/plotting/mpl/triplot.py
sigmaepsilon/plotting/mpl/utils.py
sigmaepsilon.plotting.mpl-1.0.1.dist-info/LICENSE
sigmaepsilon.plotting.mpl-1.0.1.dist-info/METADATA
sigmaepsilon.plotting.mpl-1.0.1.dist-info/WHEEL
sigmaepsilon.plotting.mpl-1.0.1.dist-info/top_level.txt
sigmaepsilon.plotting.mpl-1.0.1.dist-info/RECORD
