Metadata-Version: 2.1
Name: sigmaepsilon.plotting.mpl
Version: 1.0.1
Summary: Utilities for plotting with matplotlib.
Author-email: SigmaEpsilon <bencebalogh@sigmaepsilon.com>
Maintainer-email: SigmaEpsilon <bencebalogh@sigmaepsilon.com>
License: MIT License
Project-URL: Homepage, https://github.com/sigma-epsilon/sigmaepsilon.plotting.mpl
Keywords: engineering,mechanics
Classifier: Development Status :: 5 - Production/Stable
Classifier: License :: OSI Approved :: MIT License
Classifier: Programming Language :: Python :: 3.7
Classifier: Programming Language :: Python :: 3.8
Classifier: Programming Language :: Python :: 3.9
Classifier: Programming Language :: Python :: 3.10
Classifier: Programming Language :: Python :: 3 :: Only
Classifier: Operating System :: OS Independent
Requires-Python: <3.11,>=3.7
License-File: LICENSE
Requires-Dist: matplotlib
Requires-Dist: linkeddeepdict >=0.0.1
Requires-Dist: sigmaepsilon.mesh >=1.0.0
Provides-Extra: dev
Requires-Dist: ipykernel ; extra == 'dev'
Requires-Dist: black ; extra == 'dev'
Provides-Extra: docs
Requires-Dist: ipython ; extra == 'docs'
Requires-Dist: myst-parser ; extra == 'docs'
Requires-Dist: nbsphinx ; extra == 'docs'
Requires-Dist: sphinx-gallery ; extra == 'docs'
Requires-Dist: sphinx-copybutton ; extra == 'docs'
Requires-Dist: nbsphinx-link ; extra == 'docs'
Requires-Dist: sphinxcontrib-svg2pdfconverter ; extra == 'docs'
Requires-Dist: sphinx-design ; extra == 'docs'
Requires-Dist: sphinx-inline-tabs ; extra == 'docs'
Requires-Dist: pydata-sphinx-theme ; extra == 'docs'
Requires-Dist: matplotlib ; extra == 'docs'
Provides-Extra: test
Requires-Dist: pytest ; extra == 'test'
Requires-Dist: pytest-cov ; extra == 'test'
Requires-Dist: coverage ; extra == 'test'
